IMMerge/__init__.py
IMMerge/check_r2_setting_for_imputation.py
IMMerge/get_SNP_list.py
IMMerge/make_info.py
IMMerge/merge_files.py
IMMerge/process_args.py
IMMerge-0.0.3.dist-info/LICENSE
IMMerge-0.0.3.dist-info/METADATA
IMMerge-0.0.3.dist-info/WHEEL
IMMerge-0.0.3.dist-info/top_level.txt
IMMerge-0.0.3.dist-info/RECORD
