Metadata-Version: 2.1
Name: IMMerge
Version: 0.0.3
Home-page: https://github.com/belowlab/IMMerge
Author: Wanying Zhu from Below lab
Author-email: email@example.com
License: MIT
Keywords: Genetics imputation VCF_merger
Requires-Python: >=3
License-File: LICENSE
Requires-Dist: pandas
Requires-Dist: xopen
